sphere/flood/analysis/hazus_flood.py
sphere/flood/default_vulnerability.py
sphere/flood/py.typed
sphere/flood/single_value_reader.py
sphere_flood-0.1.3.dist-info/WHEEL
sphere_flood-0.1.3.dist-info/entry_points.txt
sphere_flood-0.1.3.dist-info/METADATA
sphere_flood-0.1.3.dist-info/RECORD
