Metadata-Version: 2.3
Name: sphere-flood
Version: 0.1.3
Summary: Add your description here
Author: Troy Schmidt
Author-email: Troy Schmidt <schmidt.troy@gmail.com>
Requires-Dist: geopandas>=1.1.1
Requires-Dist: numpy>=2.2.6
Requires-Dist: rasterio>=1.4.3
Requires-Dist: sphere-core
Requires-Dist: sphere-data
Requires-Python: >=3.10
